timsrust_pyo3-0.4.1.dist-info/METADATA
timsrust_pyo3-0.4.1.dist-info/WHEEL
timsrust_pyo3/__init__.py
timsrust_pyo3/timsrust_pyo3.cpython-311-i386-linux-gnu.so
timsrust_pyo3-0.4.1.dist-info/RECORD
