Metadata-Version: 2.4
Name: timsrust_pyo3
Version: 0.4.1
Classifier: Programming Language :: Rust
Classifier: Programming Language :: Python :: Implementation :: CPython
Classifier: Programming Language :: Python :: Implementation :: PyPy
Requires-Dist: pytest ; extra == 'test'
Requires-Dist: pytest-cov ; extra == 'test'
Requires-Dist: pytest-datadir ; extra == 'test'
Requires-Dist: black ; extra == 'lint'
Requires-Dist: ruff ; extra == 'lint'
Requires-Dist: pyyaml ; extra == 'doc'
Requires-Dist: ipykernel ; extra == 'doc'
Requires-Dist: nbformat ; extra == 'doc'
Requires-Dist: nbclient ; extra == 'doc'
Provides-Extra: test
Provides-Extra: lint
Provides-Extra: doc
License: Apache-2.0
Requires-Python: >=3.9
